pyriscv_client/__init__.py
pyriscv_client/__main__.py
pyriscv_client/components/__init__.py
pyriscv_client/components/accordion_frame.py
pyriscv_client/components/bullet_points.py
pyriscv_client/components/editor_frame.py
pyriscv_client/components/profile_generator.py
pyriscv_client/components/radar_component.py
pyriscv_client/components/rich_text.py
pyriscv_client/components/slideshow.py
pyriscv_client/components/video_player_frame.py
pyriscv_client/service/__init__.py
pyriscv_client/service/runner.py
pyriscv_client/service/submission_interface.py
pyriscv_client-0.0.1.dist-info/entry_points.txt
pyriscv_client-0.0.1.dist-info/LICENSE
pyriscv_client-0.0.1.dist-info/WHEEL
pyriscv_client-0.0.1.dist-info/METADATA
pyriscv_client-0.0.1.dist-info/RECORD
