Metadata-Version: 2.1
Name: pyriscv_client
Version: 0.0.1
Summary: Placeholder
Author-email: pyriscv <pyriscv@gmail.com>
Classifier: License :: OSI Approved :: MIT License
Classifier: Programming Language :: Python :: 3
Requires-Dist: matplotlib
Requires-Dist: pygments
Requires-Dist: numpy
Requires-Dist: tkVideoPlayer
Requires-Dist: pillow
Project-URL: Home, https://github.com/pyriscv/pyriscv
